{
    "ret":true,
    "city":"北京",
    "swiperList":[
        {
            "id":"01",
            "imgUrl":"http://img1.qunarzz.com/piao/fusion/1804/c4/1cdd28811593b802.jpg_750x200_5fbb7c91.jpg"
        },
        {
            "id":"02",
            "imgUrl":"http://img1.qunarzz.com/piao/fusion/1805/e5/59fad13a64807d02.jpg_750x200_713ae984.jpg"
        },
        {
            "id":"03",
            "imgUrl":"http://img1.qunarzz.com/piao/fusion/1804/d1/2ba49f4f21ed2102.jpg_750x200_79e641ad.jpg"
        },
        {
            "id":"04",
            "imgUrl":"http://img1.qunarzz.com/piao/fusion/1805/e4/d1086d4c5671aa02.jpg_750x200_60e211cd.jpg"
        }
    ],
    "recommed":[
        {
            "id":"001",
            "imgUrl":"http://img1.qunarzz.com/sight/source/1505/7d/df6ff468331c43.jpg_r_640x214_1f3783d0.jpg",
            "title":"上海玛雅海滩水公园",
            "desc":"走进自然或玩转乐园，感知大千世界"
        },
        {
            "id":"002",
            "imgUrl":"http://img1.qunarzz.com/sight/source/1505/7d/df6ff468331c43.jpg_r_640x214_1f3783d0.jpg",
            "title":"上海玛雅海滩水公园",
            "desc":"走进自然或玩转乐园，感知大千世界"
        },{
            "id":"003",
            "imgUrl":"http://img1.qunarzz.com/sight/source/1505/7d/df6ff468331c43.jpg_r_640x214_1f3783d0.jpg",
            "title":"上海玛雅海滩水公园",
            "desc":"走进自然或玩转乐园，感知大千世界"
        },{
            "id":"004",
            "imgUrl":"http://img1.qunarzz.com/sight/source/1505/7d/df6ff468331c43.jpg_r_640x214_1f3783d0.jpg",
            "title":"上海玛雅海滩水公园",
            "desc":"走进自然或玩转乐园，感知大千世界"
        },{
            "id":"005",
            "imgUrl":"http://img1.qunarzz.com/sight/source/1505/7d/df6ff468331c43.jpg_r_640x214_1f3783d0.jpg",
            "title":"上海玛雅海滩水公园",
            "desc":"走进自然或玩转乐园，感知大千世界"
        },{
            "id":"006",
            "imgUrl":"http://img1.qunarzz.com/sight/source/1505/7d/df6ff468331c43.jpg_r_640x214_1f3783d0.jpg",
            "title":"上海玛雅海滩水公园",
            "desc":"走进自然或玩转乐园，感知大千世界"
        },{
            "id":"007",
            "imgUrl":"http://img1.qunarzz.com/sight/source/1505/7d/df6ff468331c43.jpg_r_640x214_1f3783d0.jpg",
            "title":"上海玛雅海滩水公园",
            "desc":"走进自然或玩转乐园，感知大千世界"
        }
    ],
    "iconList":[
        {
          "id":"001",
          "content":"景点门票",
          "imgUrl":"http://img1.qunarzz.com/piao/fusion/1803/95/f3dd6c383aeb3b02.png"
        },
        {
          "id":"002",
          "content":"一日游",
          "imgUrl":"http://img1.qunarzz.com/piao/fusion/1804/5a/13ceb38dcf262f02.png"
        },
        {
          "id":"003",
          "content":"必游榜单",
          "imgUrl":"http://img1.qunarzz.com/piao/fusion/1804/ff/fdf170ee89594b02.png"
        },
        {
          "id":"004",
          "content":"动植物园",
          "imgUrl":"http://img1.qunarzz.com/piao/fusion/1803/76/eb88861d78fb9902.png"
        },
        {
          "id":"005",
          "content":"踏青赏花",
          "imgUrl":"http://img1.qunarzz.com/piao/fusion/1803/bd/9f7b9b2b60c1502.png"
        },
        {
          "id":"006",
          "content":"城市观光",
          "imgUrl":"http://img1.qunarzz.com/piao/fusion/1803/b6/37560ece9c62b502.png"
        },
        {
          "id":"007",
          "content":"上海欢乐谷",
          "imgUrl":"http://img1.qunarzz.com/piao/fusion/1803/b1/528a9e80403b8c02.png"
        },
        {
          "id":"008",
          "content":"Q+精选",
          "imgUrl":"http://img1.qunarzz.com/piao/fusion/1804/ed/cf572be30fc32f02.png"
        },
        {
          "id":"009",
          "content":"上海迪士尼",
          "imgUrl":"http://img1.qunarzz.com/piao/fusion/1803/de/f26be47a6bf02a02.png"
        }

    ]
}